odoo8_addon_stock_picking_invoicing_incoterm_sale-8.0.1.0.0.99.dev18-py2.7-nspkg.pth
odoo8_addon_stock_picking_invoicing_incoterm_sale-8.0.1.0.0.99.dev18.dist-info/DESCRIPTION.rst
odoo8_addon_stock_picking_invoicing_incoterm_sale-8.0.1.0.0.99.dev18.dist-info/METADATA
odoo8_addon_stock_picking_invoicing_incoterm_sale-8.0.1.0.0.99.dev18.dist-info/RECORD
odoo8_addon_stock_picking_invoicing_incoterm_sale-8.0.1.0.0.99.dev18.dist-info/WHEEL
odoo8_addon_stock_picking_invoicing_incoterm_sale-8.0.1.0.0.99.dev18.dist-info/metadata.json
odoo8_addon_stock_picking_invoicing_incoterm_sale-8.0.1.0.0.99.dev18.dist-info/namespace_packages.txt
odoo8_addon_stock_picking_invoicing_incoterm_sale-8.0.1.0.0.99.dev18.dist-info/top_level.txt
odoo_addons/stock_picking_invoicing_incoterm_sale/README.rst
odoo_addons/stock_picking_invoicing_incoterm_sale/__init__.py
odoo_addons/stock_picking_invoicing_incoterm_sale/__openerp__.py
odoo_addons/stock_picking_invoicing_incoterm_sale/i18n/ca.po
odoo_addons/stock_picking_invoicing_incoterm_sale/i18n/de.po
odoo_addons/stock_picking_invoicing_incoterm_sale/i18n/es.po
odoo_addons/stock_picking_invoicing_incoterm_sale/i18n/es_AR.po
odoo_addons/stock_picking_invoicing_incoterm_sale/i18n/es_MX.po
odoo_addons/stock_picking_invoicing_incoterm_sale/i18n/fi.po
odoo_addons/stock_picking_invoicing_incoterm_sale/i18n/fr.po
odoo_addons/stock_picking_invoicing_incoterm_sale/i18n/hr.po
odoo_addons/stock_picking_invoicing_incoterm_sale/i18n/hu.po
odoo_addons/stock_picking_invoicing_incoterm_sale/i18n/it.po
odoo_addons/stock_picking_invoicing_incoterm_sale/i18n/nl.po
odoo_addons/stock_picking_invoicing_incoterm_sale/i18n/nl_NL.po
odoo_addons/stock_picking_invoicing_incoterm_sale/i18n/pt.po
odoo_addons/stock_picking_invoicing_incoterm_sale/i18n/pt_BR.po
odoo_addons/stock_picking_invoicing_incoterm_sale/i18n/ro.po
odoo_addons/stock_picking_invoicing_incoterm_sale/i18n/sk.po
odoo_addons/stock_picking_invoicing_incoterm_sale/i18n/sl.po
odoo_addons/stock_picking_invoicing_incoterm_sale/i18n/tr.po
odoo_addons/stock_picking_invoicing_incoterm_sale/i18n/tr_TR.po
odoo_addons/stock_picking_invoicing_incoterm_sale/i18n/zh_CN.po
odoo_addons/stock_picking_invoicing_incoterm_sale/models/__init__.py
odoo_addons/stock_picking_invoicing_incoterm_sale/models/sale_order.py
odoo_addons/stock_picking_invoicing_incoterm_sale/models/stock_move.py
odoo_addons/stock_picking_invoicing_incoterm_sale/static/description/icon.png
odoo_addons/stock_picking_invoicing_incoterm_sale/tests/__init__.py
odoo_addons/stock_picking_invoicing_incoterm_sale/tests/test_stock_picking_invoicing_incoterm_sale.py
