Metadata-Version: 2.0
Name: odoo8-addon-stock-picking-invoicing-incoterm-sale
Version: 8.0.1.0.0.99.dev18
Summary: Copy incoterm from sale to invoice and to picking
Home-page: http://www.agilebg.com
Author: Agile Business Group, Odoo Community Association (OCA)
Author-email: support@odoo-community.org
License: AGPL-3
Platform: UNKNOWN
Classifier: Programming Language :: Python
Classifier: Framework :: Odoo
Classifier: License :: OSI Approved :: GNU Affero General Public License v3
Requires-Python: ~=2.7
Requires-Dist: odoo (<9.0a,>=8.0a)
Requires-Dist: odoo8-addon-stock-picking-invoicing-incoterm
